tusur/__init__.py
tusur/authorization.py
tusur/exceptions.py
tusur/sdo.py
tusur/session.py
tusur-0.2.0.dist-info/LICENSE
tusur-0.2.0.dist-info/METADATA
tusur-0.2.0.dist-info/WHEEL
tusur-0.2.0.dist-info/top_level.txt
tusur-0.2.0.dist-info/RECORD
